cordic_vectoring_mode.v
// CORDIC Vectoring Mode - 16 Stages
// Converts Cartesian coordinates to Polar (Magnitude & Angle)
// N-bit fixed point arithmetic, Q2.30 format (scale = 2^30)
// Input coordinates use Q2.30: real_value = fixed_value / 2^30
// Output magnitude is raw CORDIC value (scaled by K_n ~1.6468); divide by K_n to correct
// Output angle is in Q2.30 radians
// Author: CORDIC Design
// Date: 2026

module cordic_vectoring_mode #(
    parameter WIDTH = 32,           // Bit width of data
    parameter STAGES = 16,          // Number of CORDIC stages
    parameter FRAC_BITS = 30        // Fractional bits for fixed-point (Q2.30)
) (
    input clk,
    input rst,
    input valid_in,
    input signed [WIDTH-1:0] x_in,  // Input X coordinate
    input signed [WIDTH-1:0] y_in,  // Input Y coordinate
    output reg valid_out,
    output reg signed [WIDTH-1:0] magnitude, // Output magnitude
    output reg signed [WIDTH-1:0] angle      // Output angle
);

// CORDIC rotation constants
reg signed [WIDTH-1:0] atan_lut [0:15];

// Initialize LUT with precomputed atan values in Q2.30 fixed-point format
// atan(2^-i) * 2^30  for i = 0 to 15
initial begin
    atan_lut[0]  = 32'h3243F6A9;  // atan(2^0)  = 0.785398163 rad (45.0000 deg)
    atan_lut[1]  = 32'h1DAC6705;  // atan(2^-1) = 0.463647609 rad (26.5651 deg)
    atan_lut[2]  = 32'h0FADBAFD;  // atan(2^-2) = 0.244978663 rad (14.0362 deg)
    atan_lut[3]  = 32'h07F56EA7;  // atan(2^-3) = 0.124354995 rad ( 7.1250 deg)
    atan_lut[4]  = 32'h03FEAB77;  // atan(2^-4) = 0.062418810 rad ( 3.5763 deg)
    atan_lut[5]  = 32'h01FFD55C;  // atan(2^-5) = 0.031239833 rad ( 1.7899 deg)
    atan_lut[6]  = 32'h00FFFAAB;  // atan(2^-6) = 0.015623729 rad ( 0.8952 deg)
    atan_lut[7]  = 32'h007FFF55;  // atan(2^-7) = 0.007812341 rad ( 0.4476 deg)
    atan_lut[8]  = 32'h003FFFEB;  // atan(2^-8) = 0.003906230 rad ( 0.2238 deg)
    atan_lut[9]  = 32'h001FFFFD;  // atan(2^-9) = 0.001953123 rad ( 0.1119 deg)
    atan_lut[10] = 32'h00100000;  // atan(2^-10)= 0.000976562 rad ( 0.0560 deg)
    atan_lut[11] = 32'h00080000;  // atan(2^-11)= 0.000488281 rad ( 0.0280 deg)
    atan_lut[12] = 32'h00040000;  // atan(2^-12)= 0.000244141 rad ( 0.0140 deg)
    atan_lut[13] = 32'h00020000;  // atan(2^-13)= 0.000122070 rad ( 0.0070 deg)
    atan_lut[14] = 32'h00010000;  // atan(2^-14)= 0.000061035 rad ( 0.0035 deg)
    atan_lut[15] = 32'h00008000;  // atan(2^-15)= 0.000030518 rad ( 0.0017 deg)
end

reg signed [WIDTH-1:0] x_stages [0:STAGES];
reg signed [WIDTH-1:0] y_stages [0:STAGES];
reg signed [WIDTH-1:0] angle_stages [0:STAGES];
reg valid_stages [0:STAGES];

integer stage;

always @(posedge clk or posedge rst) begin
    if (rst) begin
        valid_out <= 1'b0;
        magnitude <= 32'b0;
        angle <= 32'b0;
    end else begin
        x_stages[0] <= x_in;
        y_stages[0] <= y_in;
        angle_stages[0] <= 32'b0;
        valid_stages[0] <= valid_in;
        
        // CORDIC iterations
        for (stage = 0; stage < STAGES; stage = stage + 1) begin
            if (y_stages[stage][WIDTH-1] == 1'b0) begin
                // Y is non-negative: rotate CW to drive Y toward zero
                x_stages[stage+1] <= x_stages[stage] + (y_stages[stage] >>> stage);
                y_stages[stage+1] <= y_stages[stage] - (x_stages[stage] >>> stage);
                angle_stages[stage+1] <= angle_stages[stage] + atan_lut[stage];
            end else begin
                // Y is negative: rotate CCW to drive Y toward zero
                x_stages[stage+1] <= x_stages[stage] - (y_stages[stage] >>> stage);
                y_stages[stage+1] <= y_stages[stage] + (x_stages[stage] >>> stage);
                angle_stages[stage+1] <= angle_stages[stage] - atan_lut[stage];
            end
            valid_stages[stage+1] <= valid_stages[stage];
        end
        
        magnitude <= x_stages[STAGES];
        angle <= angle_stages[STAGES];
        valid_out <= valid_stages[STAGES];
    end
end

endmodule

cordic_rotation_mode.v
// CORDIC Rotation Mode - 16 Stages
// Rotates an input vector by a given angle
// N-bit fixed point arithmetic, Q2.30 format (scale = 2^30)
// Input/output coordinates and angle use Q2.30: real_value = fixed_value / 2^30
// Note: CORDIC gain K_n ~1.6468 is applied to output magnitude; divide by K_n to correct
// Author: CORDIC Design
// Date: 2026

module cordic_rotation_mode #(
    parameter WIDTH = 32,           // Bit width of data
    parameter STAGES = 16,          // Number of CORDIC stages
    parameter FRAC_BITS = 30        // Fractional bits for fixed-point (Q2.30)
) (
    input clk,
    input rst,
    input valid_in,
    input signed [WIDTH-1:0] x_in,  // Input X coordinate
    input signed [WIDTH-1:0] y_in,  // Input Y coordinate
    input signed [WIDTH-1:0] angle_in, // Input rotation angle (in fixed-point radians)
    output reg valid_out,
    output reg signed [WIDTH-1:0] x_out, // Rotated X
    output reg signed [WIDTH-1:0] y_out, // Rotated Y
    output reg signed [WIDTH-1:0] angle_out // Remaining angle
);

// CORDIC rotation constants (precomputed atan values in fixed-point)
// atan(2^-i) for i = 0 to 15
reg signed [WIDTH-1:0] atan_lut [0:15];

integer i, stage;
reg signed [WIDTH-1:0] x_temp, y_temp, angle_temp;
reg signed [WIDTH-1:0] x_shift, y_shift;
reg signed [WIDTH-1:0] x_stages [0:STAGES];
reg signed [WIDTH-1:0] y_stages [0:STAGES];
reg signed [WIDTH-1:0] angle_stages [0:STAGES];
reg valid_stages [0:STAGES];

// Initialize LUT with precomputed atan values in Q2.30 fixed-point format
// atan(2^-i) * 2^30  for i = 0 to 15
initial begin
    atan_lut[0]  = 32'h3243F6A9;  // atan(2^0)  = 0.785398163 rad (45.0000 deg)
    atan_lut[1]  = 32'h1DAC6705;  // atan(2^-1) = 0.463647609 rad (26.5651 deg)
    atan_lut[2]  = 32'h0FADBAFD;  // atan(2^-2) = 0.244978663 rad (14.0362 deg)
    atan_lut[3]  = 32'h07F56EA7;  // atan(2^-3) = 0.124354995 rad ( 7.1250 deg)
    atan_lut[4]  = 32'h03FEAB77;  // atan(2^-4) = 0.062418810 rad ( 3.5763 deg)
    atan_lut[5]  = 32'h01FFD55C;  // atan(2^-5) = 0.031239833 rad ( 1.7899 deg)
    atan_lut[6]  = 32'h00FFFAAB;  // atan(2^-6) = 0.015623729 rad ( 0.8952 deg)
    atan_lut[7]  = 32'h007FFF55;  // atan(2^-7) = 0.007812341 rad ( 0.4476 deg)
    atan_lut[8]  = 32'h003FFFEB;  // atan(2^-8) = 0.003906230 rad ( 0.2238 deg)
    atan_lut[9]  = 32'h001FFFFD;  // atan(2^-9) = 0.001953123 rad ( 0.1119 deg)
    atan_lut[10] = 32'h00100000;  // atan(2^-10)= 0.000976562 rad ( 0.0560 deg)
    atan_lut[11] = 32'h00080000;  // atan(2^-11)= 0.000488281 rad ( 0.0280 deg)
    atan_lut[12] = 32'h00040000;  // atan(2^-12)= 0.000244141 rad ( 0.0140 deg)
    atan_lut[13] = 32'h00020000;  // atan(2^-13)= 0.000122070 rad ( 0.0070 deg)
    atan_lut[14] = 32'h00010000;  // atan(2^-14)= 0.000061035 rad ( 0.0035 deg)
    atan_lut[15] = 32'h00008000;  // atan(2^-15)= 0.000030518 rad ( 0.0017 deg)
end

// Pipeline stages
always @(posedge clk or posedge rst) begin
    if (rst) begin
        valid_out <= 1'b0;
        x_out <= 32'b0;
        y_out <= 32'b0;
        angle_out <= 32'b0;
    end else begin
        // Initialize first stage
        x_stages[0] <= x_in;
        y_stages[0] <= y_in;
        angle_stages[0] <= angle_in;
        valid_stages[0] <= valid_in;
        
        // CORDIC iterations (16 stages)
        for (stage = 0; stage < STAGES; stage = stage + 1) begin
            if (angle_stages[stage][WIDTH-1] == 1'b1) begin
                // Angle is negative, rotate clockwise (subtract angle)
                x_stages[stage+1] <= x_stages[stage] + (y_stages[stage] >>> stage);
                y_stages[stage+1] <= y_stages[stage] - (x_stages[stage] >>> stage);
                angle_stages[stage+1] <= angle_stages[stage] + atan_lut[stage];
            end else begin
                // Angle is positive, rotate counter-clockwise (add angle)
                x_stages[stage+1] <= x_stages[stage] - (y_stages[stage] >>> stage);
                y_stages[stage+1] <= y_stages[stage] + (x_stages[stage] >>> stage);
                angle_stages[stage+1] <= angle_stages[stage] - atan_lut[stage];
            end
            valid_stages[stage+1] <= valid_stages[stage];
        end
        
        // Output from last stage
        x_out <= x_stages[STAGES];
        y_out <= y_stages[STAGES];
        angle_out <= angle_stages[STAGES];
        valid_out <= valid_stages[STAGES];
    end
end

endmodule

cordic_tb.v
`timescale 1ns / 1ps

module cordic_tb;

parameter WIDTH = 32;
parameter STAGES = 16;
parameter FRAC_BITS = 30;   // Q2.30: real_value = fixed_value / 2^30
parameter CLK_PERIOD = 10;

reg clk, rst;
reg valid_in;
reg signed [WIDTH-1:0] x_in, y_in;
reg signed [WIDTH-1:0] angle_in, x_vec_in, y_vec_in;

wire valid_out_rot;
wire signed [WIDTH-1:0] x_out_rot, y_out_rot, angle_out_rot;

wire valid_out_vec;
wire signed [WIDTH-1:0] magnitude, angle_out_vec;

// Instantiate modules
cordic_rotation_mode #(.WIDTH(WIDTH), .STAGES(STAGES), .FRAC_BITS(FRAC_BITS))
    dut_rot (
        .clk(clk), .rst(rst), .valid_in(valid_in),
        .x_in(x_in), .y_in(y_in), .angle_in(angle_in),
        .valid_out(valid_out_rot), .x_out(x_out_rot), .y_out(y_out_rot), .angle_out(angle_out_rot)
    );

cordic_vectoring_mode #(.WIDTH(WIDTH), .STAGES(STAGES), .FRAC_BITS(FRAC_BITS))
    dut_vec (
        .clk(clk), .rst(rst), .valid_in(valid_in),
        .x_in(x_vec_in), .y_in(y_vec_in),
        .valid_out(valid_out_vec), .magnitude(magnitude), .angle(angle_out_vec)
    );

// Clock generation
initial begin
    clk = 0;
    forever #(CLK_PERIOD/2) clk = ~clk;
end

// Test stimuli
initial begin
    rst = 1;
    valid_in = 0;
    x_in = 0;
    y_in = 0;
    angle_in = 0;
    x_vec_in = 0;
    y_vec_in = 0;
    
    #20 rst = 0;
    
    // Test rotation mode: rotate (1.0, 0.0) by 45 degrees
    // x_in = 1.0 in Q2.30 = 0x40000000
    // angle_in = pi/4 in Q2.30 = 0x3243F6A9
    // Expected output (raw, includes K_n~1.6468 gain):
    //   x_out ~ K_n*cos(45) ~ 1.164 → 0x4A72_7E68
    //   y_out ~ K_n*sin(45) ~ 1.164 → 0x4A72_7E68
    #10 valid_in = 1; x_in = 32'h4000_0000; y_in = 0; angle_in = 32'h3243_F6A9;
    #10 valid_in = 0;
    
    // Test vectoring mode: convert (0.5, 0.5) to polar
    // x_vec_in = y_vec_in = 0.5 in Q2.30 = 0x20000000
    // (Note: inputs must satisfy K_n*sqrt(x^2+y^2) < 2.0 to avoid Q2.30 overflow)
    // Expected output (raw, includes K_n~1.6468 gain):
    //   magnitude ~ K_n*sqrt(0.5^2+0.5^2) ~ 1.164 → 0x4A86_1BD2
    //   angle = 45 deg = pi/4 in Q2.30 → ~0x3244_37C9
    #100 valid_in = 1; x_vec_in = 32'h2000_0000; y_vec_in = 32'h2000_0000;
    #10 valid_in = 0;
    
    #500 $finish;
end

// Monitor output
initial begin
    $monitor("Time=%0t | ROT: valid=%b x=%h y=%h | VEC: valid=%b mag=%h angle=%h",
             $time, valid_out_rot, x_out_rot, y_out_rot, valid_out_vec, magnitude, angle_out_vec);
end

initial begin
    $dumpfile("cordic_tb.vcd");
    $dumpvars(0, cordic_tb);
end

endmodule

cordic_tb.vcd
$date
	Tue Apr 28 08:12:55 2026
$end
$version
	Icarus Verilog
$end
$timescale
	1ps
$end
$scope module cordic_tb $end
$var wire 32 ! y_out_rot [31:0] $end
$var wire 32 " x_out_rot [31:0] $end
$var wire 1 # valid_out_vec $end
$var wire 1 $ valid_out_rot $end
$var wire 32 % magnitude [31:0] $end
$var wire 32 & angle_out_vec [31:0] $end
$var wire 32 ' angle_out_rot [31:0] $end
$var parameter 32 ( CLK_PERIOD $end
$var parameter 32 ) FRAC_BITS $end
$var parameter 32 * STAGES $end
$var parameter 32 + WIDTH $end
$var reg 32 , angle_in [31:0] $end
$var reg 1 - clk $end
$var reg 1 . rst $end
$var reg 1 / valid_in $end
$var reg 32 0 x_in [31:0] $end
$var reg 32 1 x_vec_in [31:0] $end
$var reg 32 2 y_in [31:0] $end
$var reg 32 3 y_vec_in [31:0] $end
$scope module dut_rot $end
$var wire 32 4 angle_in [31:0] $end
$var wire 1 - clk $end
$var wire 1 . rst $end
$var wire 1 / valid_in $end
$var wire 32 5 x_in [31:0] $end
$var wire 32 6 y_in [31:0] $end
$var parameter 32 7 FRAC_BITS $end
$var parameter 32 8 STAGES $end
$var parameter 32 9 WIDTH $end
$var reg 32 : angle_out [31:0] $end
$var reg 1 $ valid_out $end
$var reg 32 ; x_out [31:0] $end
$var reg 32 < y_out [31:0] $end
$var integer 32 = stage [31:0] $end
$upscope $end
$scope module dut_vec $end
$var wire 1 - clk $end
$var wire 1 . rst $end
$var wire 1 / valid_in $end
$var wire 32 > x_in [31:0] $end
$var wire 32 ? y_in [31:0] $end
$var parameter 32 @ FRAC_BITS $end
$var parameter 32 A STAGES $end
$var parameter 32 B WIDTH $end
$var reg 32 C angle [31:0] $end
$var reg 32 D magnitude [31:0] $end
$var reg 1 # valid_out $end
$var integer 32 E stage [31:0] $end
$upscope $end
$upscope $end
$enddefinitions $end
$comment Show the parameter values. $end
$dumpall
b100000 B
b10000 A
b11110 @
b100000 9
b10000 8
b11110 7
b100000 +
b10000 *
b11110 )
b1010 (
$end
#0
$dumpvars
bx E
b0 D
b0 C
b0 ?
b0 >
bx =
b0 <
b0 ;
b0 :
b0 6
b0 5
b0 4
b0 3
b0 2
b0 1
b0 0
0/
1.
0-
b0 ,
b0 '
b0 &
b0 %
0$
0#
b0 "
b0 !
$end
#5000
1-
#10000
0-
#15000
1-
#20000
0-
0.
#25000
x#
bx &
bx C
bx %
bx D
x$
bx '
bx :
bx !
bx <
bx "
bx ;
b10000 E
b10000 =
1-
#30000
0-
b110010010000111111011010101001 ,
b110010010000111111011010101001 4
b1000000000000000000000000000000 0
b1000000000000000000000000000000 5
1/
#35000
b10000 =
b10000 E
1-
#40000
0-
0/
#45000
b10000 E
b10000 =
1-
#50000
0-
#55000
b10000 =
b10000 E
1-
#60000
0-
#65000
b10000 E
b10000 =
1-
#70000
0-
#75000
b10000 =
b10000 E
1-
#80000
0-
#85000
b10000 E
b10000 =
1-
#90000
0-
#95000
b10000 =
b10000 E
1-
#100000
0-
#105000
b10000 E
b10000 =
1-
#110000
0-
#115000
b10000 =
b10000 E
1-
#120000
0-
#125000
b10000 E
b10000 =
1-
#130000
0-
#135000
b10000 =
b10000 E
1-
#140000
0-
b100000000000000000000000000000 3
b100000000000000000000000000000 ?
b100000000000000000000000000000 1
b100000000000000000000000000000 >
1/
#145000
b10000 E
b10000 =
1-
#150000
0-
0/
#155000
b10000 =
b10000 E
1-
#160000
0-
#165000
b10000 E
b10000 =
1-
#170000
0-
#175000
b10000 =
b10000 E
1-
#180000
0-
#185000
b10000 E
b10000 =
1-
#190000
0-
#195000
0$
b100100111001101 '
b100100111001101 :
b0 !
b0 <
b0 "
b0 ;
0#
b1101111100100011000001000001101 &
b1101111100100011000001000001101 C
b0 %
b0 D
b10000 =
b10000 E
1-
#200000
0-
#205000
1#
1$
b11111111111111111011111011100000 '
b11111111111111111011111011100000 :
b1001010100001100110011110101000 !
b1001010100001100110011110101000 <
b1001010100001011100111111111111 "
b1001010100001011100111111111111 ;
b10000 E
b10000 =
1-
#210000
0-
#215000
0$
0#
b10000 =
b10000 E
1-
#220000
0-
#225000
b10000 E
b10000 =
1-
#230000
0-
#235000
b10000 =
b10000 E
1-
#240000
0-
#245000
b10000 E
b10000 =
1-
#250000
0-
#255000
b10000 =
b10000 E
1-
#260000
0-
#265000
b10000 E
b10000 =
1-
#270000
0-
#275000
b10000 =
b10000 E
1-
#280000
0-
#285000
b10000 E
b10000 =
1-
#290000
0-
#295000
b10000 =
b10000 E
1-
#300000
0-
#305000
b10000 E
b10000 =
1-
#310000
0-
#315000
1$
1#
b110010010001000011011111001001 &
b110010010001000011011111001001 C
b1001010100001100001101111010010 %
b1001010100001100001101111010010 D
b10000 =
b10000 E
1-
#320000
0-
#325000
0#
0$
b10000 E
b10000 =
1-
#330000
0-
#335000
b10000 =
b10000 E
1-
#340000
0-
#345000
b10000 E
b10000 =
1-
#350000
0-
#355000
b10000 =
b10000 E
1-
#360000
0-
#365000
b10000 E
b10000 =
1-
#370000
0-
#375000
b10000 =
b10000 E
1-
#380000
0-
#385000
b10000 E
b10000 =
1-
#390000
0-
#395000
b10000 =
b10000 E
1-
#400000
0-
#405000
b10000 E
b10000 =
1-
#410000
0-
#415000
b10000 =
b10000 E
1-
#420000
0-
#425000
b10000 E
b10000 =
1-
#430000
0-
#435000
b10000 =
b10000 E
1-
#440000
0-
#445000
b10000 E
b10000 =
1-
#450000
0-
#455000
b10000 =
b10000 E
1-
#460000
0-
#465000
b10000 E
b10000 =
1-
#470000
0-
#475000
b10000 =
b10000 E
1-
#480000
0-
#485000
b10000 E
b10000 =
1-
#490000
0-
#495000
b10000 =
b10000 E
1-
#500000
0-
#505000
b10000 E
b10000 =
1-
#510000
0-
#515000
b10000 =
b10000 E
1-
#520000
0-
#525000
b10000 E
b10000 =
1-
#530000
0-
#535000
b10000 =
b10000 E
1-
#540000
0-
#545000
b10000 E
b10000 =
1-
#550000
0-
#555000
b10000 =
b10000 E
1-
#560000
0-
#565000
b10000 E
b10000 =
1-
#570000
0-
#575000
b10000 =
b10000 E
1-
#580000
0-
#585000
b10000 E
b10000 =
1-
#590000
0-
#595000
b10000 =
b10000 E
1-
#600000
0-
#605000
b10000 E
b10000 =
1-
#610000
0-
#615000
b10000 =
b10000 E
1-
#620000
0-
#625000
b10000 E
b10000 =
1-
#630000
0-
#635000
b10000 =
b10000 E
1-
#640000
0-
#645000
b10000 E
b10000 =
1-
